{"name":"Gry na codzień","tagline":"","body":"# W co warto zagrać?\r\n\r\nMamy dziś dostępne setki, jeśli nie tysiące gier na rynku. Lwia część oczywiście umyka naszej uwadze, bo nie sposób poznać je wszystkie. Postanowiłem przybliżyć, więc kilka moich ulubionych tytułów. Będzie to lista subiektywna, i nawet tematyczna. Zaprezentuję gry stricte z kanonu post-apokalipsy.\r\n\r\n# Czym jest post-apokalipsa?\r\n\r\nW odniesieniu do gier, są to tytuły, których fabuła osadzona jest w świecie, który człowiek zdołał zniszczyć. Ludzkość jest przetrzebiona, przemysł nie istnieje, Ziemia jest ledwie zamieszkiwalna, a ze wsząd na człowieka czyha masa niebezpieczeństw.\r\n\r\n# Fallout [link](http://fallout.bethsoft.com/)\r\n\r\n![Waszyngton DC](http://muve-img.cenega.pl/uploads/screens/5f73a8549724326b606673d9f2352254__fallout_3_-pc-scr_001-1280x720.jpg)\r\n\r\nFallout jest najpopularniejszym tytułem klimatów postapo. Jego główną zaletą jest przede wszystkim grywalność oraz groteskowe podejście do tematu. Dwugłowe zmutowane krowy zwane Brahminami, metrowe karaluchy, mówiące drzewa, przyjazne ghoule, oraz  masa odniesień do biektów pop kultury - to i wiele innych smaczków na pewno sprawia, iż ciężki klimat zniszczonego świata jest dostępny dla szerszej publiczności.","google":"","note":"Don't delete this file! It's used internally to help with page regeneration."}